tapeimgr/__init__.py
tapeimgr/__main__.py
tapeimgr/cli.py
tapeimgr/config.py
tapeimgr/configure.py
tapeimgr/gui.py
tapeimgr/shared.py
tapeimgr/tape.py
tapeimgr/tapeimgr.py
tapeimgr/icons/tapeimgr.png
tapeimgr/pkexec/com.ubuntu.pkexec.tapeimgr.policy
tapeimgr/pkexec/tapeimgr-pkexec
tapeimgr-0.5.0.dist-info/DESCRIPTION.rst
tapeimgr-0.5.0.dist-info/METADATA
tapeimgr-0.5.0.dist-info/RECORD
tapeimgr-0.5.0.dist-info/WHEEL
tapeimgr-0.5.0.dist-info/entry_points.txt
tapeimgr-0.5.0.dist-info/metadata.json
tapeimgr-0.5.0.dist-info/top_level.txt
