Metadata-Version: 2.0
Name: tapeimgr
Version: 0.5.0
Summary: Tape imager
Home-page: https://github.com/KBNLresearch/tapeimgr
Author: Johan van der Knijff
Author-email: johan.vanderknijff@kb.nl
Maintainer: Johan van der Knijff
Maintainer-email: johan.vanderknijff@kb.nl
License: Apache License 2.0
Download-URL: https://github.com/KBNLresearch/tapeimgr/archive/0.5.0.tar.gz
Platform: linux
Classifier: Programming Language :: Python :: 3
Requires-Python: >=3.2
Requires-Dist: setuptools
Requires-Dist: pytz
Requires-Dist: tkfilebrowser
